fdb/__init__.py
fdb/blr.py
fdb/fbcore.py
fdb/gstat.py
fdb/ibase.py
fdb/log.py
fdb/monitor.py
fdb/schema.py
fdb/services.py
fdb/trace.py
fdb/utils.py
fdb-2.0.1.dist-info/LICENSE.txt
fdb-2.0.1.dist-info/METADATA
fdb-2.0.1.dist-info/RECORD
fdb-2.0.1.dist-info/WHEEL
fdb-2.0.1.dist-info/top_level.txt
