Metadata-Version: 2.1
Name: fdb
Version: 2.0.1
Summary: The Python driver for Firebird
Home-page: https://github.com/FirebirdSQL/fdb
Author: Pavel Císař
Author-email: pcisar@users.sourceforge.net
License: UNKNOWN
Project-URL: Funding, https://www.firebirdsql.org/en/donate/
Project-URL: Documentation, http://fdb2.readthedocs.io/en/latest/
Project-URL: Bug Reports, http://tracker.firebirdsql.org/browse/PYFB
Project-URL: Say Thanks!, https://saythanks.io/to/pcisar
Project-URL: Source, https://github.com/FirebirdSQL/fdb
Keywords: Firebird
Platform: UNKNOWN
Classifier: Development Status :: 5 - Production/Stable
Classifier: Intended Audience :: Developers
Classifier: License :: OSI Approved :: BSD License
Classifier: Programming Language :: Python :: 2
Classifier: Programming Language :: Python :: 2.7
Classifier: Programming Language :: Python :: 3
Classifier: Programming Language :: Python :: 3.4
Classifier: Programming Language :: Python :: 3.5
Classifier: Programming Language :: Python :: 3.6
Classifier: Operating System :: POSIX :: Linux
Classifier: Operating System :: Microsoft :: Windows
Classifier: Operating System :: MacOS
Classifier: Topic :: Database
Requires-Python: >=2.7, !=3.0.*, !=3.1.*, !=3.2.*, !=3.3.*, <4
